odoo10_addon_hr_timesheet_activity_begin_end-10.0.1.0.0-py2.7-nspkg.pth
odoo/addons/hr_timesheet_activity_begin_end/README.rst
odoo/addons/hr_timesheet_activity_begin_end/__init__.py
odoo/addons/hr_timesheet_activity_begin_end/__manifest__.py
odoo/addons/hr_timesheet_activity_begin_end/i18n/fr.po
odoo/addons/hr_timesheet_activity_begin_end/models/__init__.py
odoo/addons/hr_timesheet_activity_begin_end/models/account_analytic_line.py
odoo/addons/hr_timesheet_activity_begin_end/static/description/icon.png
odoo/addons/hr_timesheet_activity_begin_end/tests/__init__.py
odoo/addons/hr_timesheet_activity_begin_end/tests/test_timesheet_begin_end.py
odoo/addons/hr_timesheet_activity_begin_end/views/hr_analytic_timesheet.xml
odoo/addons/hr_timesheet_activity_begin_end/views/hr_timesheet_sheet.xml
odoo10_addon_hr_timesheet_activity_begin_end-10.0.1.0.0.dist-info/DESCRIPTION.rst
odoo10_addon_hr_timesheet_activity_begin_end-10.0.1.0.0.dist-info/METADATA
odoo10_addon_hr_timesheet_activity_begin_end-10.0.1.0.0.dist-info/RECORD
odoo10_addon_hr_timesheet_activity_begin_end-10.0.1.0.0.dist-info/WHEEL
odoo10_addon_hr_timesheet_activity_begin_end-10.0.1.0.0.dist-info/metadata.json
odoo10_addon_hr_timesheet_activity_begin_end-10.0.1.0.0.dist-info/namespace_packages.txt
odoo10_addon_hr_timesheet_activity_begin_end-10.0.1.0.0.dist-info/top_level.txt
